stapler/__init__.py
stapler/forms.py
django_stapler-1.1.0.2.dist-info/LICENSE
django_stapler-1.1.0.2.dist-info/METADATA
django_stapler-1.1.0.2.dist-info/WHEEL
django_stapler-1.1.0.2.dist-info/top_level.txt
django_stapler-1.1.0.2.dist-info/RECORD
