Metadata-Version: 2.1
Name: django-stapler
Version: 1.1.0.2
Summary: A package providing a multi-ModelForm solution for django
Home-page: https://github.com/danjer/django-stapler
Author: Daan van den Akker
License: MIT
Platform: UNKNOWN
Requires-Python: >=3.6
Requires-Dist: Django (>=2.2)
